setup.py
pk_client/__init__.py
pk_client_python.egg-info/PKG-INFO
pk_client_python.egg-info/SOURCES.txt
pk_client_python.egg-info/dependency_links.txt
pk_client_python.egg-info/requires.txt
pk_client_python.egg-info/top_level.txt