Metadata-Version: 1.0
Name: pk-client-python
Version: 0.4
Summary: Python client API for the pk port knocking server daemon
Home-page: https://github.com/anrosent/pk-client-python
Author: Anson Rosenthal
Author-email: anson.rosenthal@gmail.com
License: UNKNOWN
Platform: UNKNOWN
